{
  "id": "p2p-basic",
  "name": "Procure to Pay (Basic)",
  "nodes": [
    {
      "id": "vendor-onboarding",
      "data": { "label": "Vendor Master", "level": "basic" },
      "position": { "x": 100, "y": 0 }
    },
    {
      "id": "requisition-po",
      "data": { "label": "Purchase Requisition", "level": "basic" },
      "position": { "x": 100, "y": 150 }
    },
    {
      "id": "purchase-orders",
      "data": { "label": "Purchase Order", "level": "basic" },
      "position": { "x": 100, "y": 300 }
    },
    {
      "id": "warehouse-receiving",
      "data": { "label": "Goods Receipt", "level": "basic" },
      "position": { "x": 100, "y": 450 }
    },
    {
      "id": "payment-processing",
      "data": { "label": "A/P & Payment", "level": "basic" },
      "position": { "x": 100, "y": 600 }
    }
  ],
  "edges": [
    { "id": "e1", "source": "vendor-onboarding", "target": "requisition-po", "animated": true },
    { "id": "e2", "source": "requisition-po", "target": "purchase-orders", "animated": true },
    { "id": "e3", "source": "purchase-orders", "target": "warehouse-receiving", "animated": true },
    { "id": "e4", "source": "warehouse-receiving", "target": "payment-processing", "animated": true }
  ]
}
